dj_json_env.py
setup.py
dj_json_env.egg-info/PKG-INFO
dj_json_env.egg-info/SOURCES.txt
dj_json_env.egg-info/dependency_links.txt
dj_json_env.egg-info/not-zip-safe
dj_json_env.egg-info/top_level.txt
scripts/export_json